tl_bot/__init__.py
tl_bot/cli.py
tl_bot/config.ini
tl_bot/config.py
tl_bot/main.py
tl_bot/utils.py
tl_bot-0.1.4.dist-info/licenses/LICENSE
tl_bot-0.1.4.dist-info/METADATA
tl_bot-0.1.4.dist-info/WHEEL
tl_bot-0.1.4.dist-info/entry_points.txt
tl_bot-0.1.4.dist-info/top_level.txt
tl_bot-0.1.4.dist-info/RECORD
