Metadata-Version: 2.4
Name: tl-bot
Version: 0.1.4
Summary: upload files to your telegram channel or group with your telegram bot
Home-page: https://github.com/jakbin/t-bot
Author: Jak Bin
Author-email: jakbin4747@gmail.com
Project-URL: Bug Tracker, https://github.com/jakbin/t-bot/issues
Keywords: telegram,t-bot,telegram-api,telegram-api-bot,telegram-file-upload,telegram-upload
Classifier: Programming Language :: Python :: 3.6
Classifier: License :: OSI Approved :: MIT License
Classifier: Natural Language :: English
Classifier: Operating System :: OS Independent
Requires-Python: >=3
License-File: LICENSE
Requires-Dist: tqdm
Requires-Dist: requests
Requires-Dist: requests-toolbelt
Requires-Dist: appdirs
Dynamic: author
Dynamic: author-email
Dynamic: classifier
Dynamic: description
Dynamic: description-content-type
Dynamic: home-page
Dynamic: keywords
Dynamic: license-file
Dynamic: project-url
Dynamic: requires-dist
Dynamic: requires-python
Dynamic: summary
